netdisco/__init__.py
netdisco/__main__.py
netdisco/const.py
netdisco/discovery.py
netdisco/mdns.py
netdisco/service.py
netdisco/ssdp.py
netdisco/util.py
netdisco/discoverables/__init__.py
netdisco/discoverables/arduino.py
netdisco/discoverables/home_assistant.py
netdisco/discoverables/homekit.py
netdisco/discoverables/huawei_router.py
netdisco/discoverables/xiaomi_gw.py
netdisco/discoverables/yeelight.py
networkDiscovery-1.0.0.dist-info/METADATA
networkDiscovery-1.0.0.dist-info/WHEEL
networkDiscovery-1.0.0.dist-info/top_level.txt
networkDiscovery-1.0.0.dist-info/RECORD
