Metadata-Version: 2.1
Name: networkDiscovery
Version: 1.0.0
Summary: Discover devices on your local network
Home-page: https://gitee.com/GokGok/network-discovery.git
Author: championchangpeng
Author-email: championchangpeng@gmail.com
License: Apache License 2.0
Platform: UNKNOWN
Classifier: Development Status :: 5 - Production/Stable
Classifier: Environment :: Console
Classifier: Intended Audience :: Developers
Classifier: License :: OSI Approved :: Apache Software License
Classifier: Operating System :: POSIX
Classifier: Programming Language :: Python :: 3
Classifier: Topic :: Utilities
Classifier: Topic :: Home Automation
Classifier: Topic :: System :: Networking
Requires-Python: >=3
Requires-Dist: requests (>=2.0)
Requires-Dist: zeroconf (>=0.27.1)
